pythoncharmers_meta/__init__.py
pythoncharmers_meta/ai_magic.py
pythoncharmers_meta/nb_magic.py
pythoncharmers_meta/.claude/settings.local.json
pythoncharmers_meta-0.7.8.dist-info/METADATA
pythoncharmers_meta-0.7.8.dist-info/WHEEL
pythoncharmers_meta-0.7.8.dist-info/licenses/LICENSE
pythoncharmers_meta-0.7.8.dist-info/RECORD
